{"kind":"identitytoolkit#DownloadAccountResponse","users":[{"localId":"dlaVFG8WNoaE9kAWoG5IVVwHWeqG","createdAt":"1676698826172","lastLoginAt":"1676698994234","displayName":"Otter Raccoon","providerUserInfo":[{"providerId":"google.com","rawId":"3899633265071612779834714141653431601755","federatedId":"3899633265071612779834714141653431601755","displayName":"Otter Raccoon","email":"otter.raccoon.375@example.com","screenName":"raccoon_otter"}],"validSince":"1676699073","email":"otter.raccoon.375@example.com","emailVerified":true,"disabled":false}]}